{
 "based_on": "violation_date",
 "chart_name": "Violations By Type",
 "chart_type": "Count",
 "creation": "2025-02-06 20:50:20.614813",
 "docstatus": 0,
 "doctype": "Dashboard Chart",
 "document_type": "Violations",
 "dynamic_filters_json": "[]",
 "filters_json": "[[\"Violations\",\"id_violation_type\",\"=\",\"1\",false]]",
 "group_by_type": "Count",
 "idx": 4,
 "is_public": 1,
 "is_standard": 1,
 "last_synced_on": "2025-02-06 21:08:06.832186",
 "modified": "2025-02-06 21:14:03.561331",
 "modified_by": "Administrator",
 "module": "Traffic Violation",
 "name": "Violations By Type",
 "number_of_groups": 0,
 "owner": "Administrator",
 "parent_document_type": "",
 "roles": [],
 "source": "",
 "time_interval": "Yearly",
 "timeseries": 1,
 "timespan": "Select Date Range",
 "type": "Bar",
 "use_report_chart": 0,
 "value_based_on": "",
 "y_axis": []
}